guet/__init__.py
guet/constants.py
guet/errors.py
guet/main.py
guet/commands/__init__.py
guet/commands/_command_factory.py
guet/commands/_command_map.py
guet/commands/add/__init__.py
guet/commands/add/_add.py
guet/commands/add/_add_committer.py
guet/commands/add/_args.py
guet/commands/add/_local_file_initialization.py
guet/commands/add/_overwrite.py
guet/commands/get/__init__.py
guet/commands/get/_action.py
guet/commands/get/_get.py
guet/commands/help/__init__.py
guet/commands/help/_help.py
guet/commands/help/_unknown.py
guet/commands/help/_usage.py
guet/commands/init/__init__.py
guet/commands/init/_cancel_create_hook.py
guet/commands/init/_change_hooks_folder.py
guet/commands/init/_create_hooks_alongside.py
guet/commands/init/_create_hooks_normally.py
guet/commands/init/_init.py
guet/commands/remove/__init__.py
guet/commands/remove/_remove.py
guet/commands/remove/_remove_committer.py
guet/commands/set/__init__.py
guet/commands/set/_set.py
guet/commands/set/_set_committers.py
guet/commands/yeet/__init__.py
guet/commands/yeet/_remove_global.py
guet/commands/yeet/_remove_local.py
guet/commands/yeet/_yeet.py
guet/committers/__init__.py
guet/committers/_add_committer.py
guet/committers/_comitters_printer.py
guet/committers/_committer_print_formatter.py
guet/committers/_committers2.py
guet/committers/_committers2_state.py
guet/committers/_committers_set.py
guet/committers/_current_committers.py
guet/committers/_global_committer_state.py
guet/committers/_initials_for_project.py
guet/committers/_initials_formatter.py
guet/committers/_initials_name_email_printer.py
guet/committers/_local_committers_state.py
guet/committers/_set_current_committers.py
guet/committers/committer.py
guet/config/__init__.py
guet/config/already_initialized.py
guet/config/errors.py
guet/config/set_errors.py
guet/files/__init__.py
guet/files/_file.py
guet/files/_file_system.py
guet/files/read_lines.py
guet/files/write_lines.py
guet/git/__init__.py
guet/git/_all_guet_hooks.py
guet-3.0.1.dist-info/LICENSE
guet-3.0.1.dist-info/METADATA
guet-3.0.1.dist-info/WHEEL
guet-3.0.1.dist-info/entry_points.txt
guet-3.0.1.dist-info/top_level.txt
guet-3.0.1.dist-info/RECORD
