Metadata-Version: 2.1
Name: guet
Version: 3.0.1
Summary: Enable contribution tracking when pair programming
Home-page: https://github.com/chiptopher/guet
License: UNKNOWN
Keywords: pair programming
Platform: UNKNOWN
